zhfirstpypi/__init__.py
zhfirstpypi/main.py
zhfirstpypi-0.1.0.dist-info/entry_points.txt
zhfirstpypi-0.1.0.dist-info/WHEEL
zhfirstpypi-0.1.0.dist-info/METADATA
zhfirstpypi-0.1.0.dist-info/RECORD
